[{"clientName":"Susan Lispinsky","email":"susanl@gmail.com","message":"I'd like to add my establishment to the website please."},{"clientName":"Marie Debussey","email":"mariedub@outlook.com","message":"Hello. I'd like to cancel a booking. Can you assist me?"},{"clientName":"Vegard Andersen","email":"vegard@gmail.com","message":"Hello. I didn't enjoy the last place I stayed at and would like to make a complaint."},{"clientName":"Carl Benjamin","email":"calbenjamin@gmail.com","message":"Hello, i would like to cancel my order, something has come up."},{"clientName":"Ola Normann","email":"olanormann@email.com","message":"I would like to extend my stay. The service here is amazing."},{"clientName":"Bob Rohan","email":"bobrohan@gmail.com","message":"The house keeping at my last destination was less than acceptable. please take care of it."},{"clientName":"Lisa Gjerterudsen","email":"gjerterud@epost.no","message":"I enjoyed staying at my last destination, no bathtub, 4\/5"},{"clientName":"Tormod Fredrol","email":"yourfather@yahoo.no","message":"E finn ikke mine bil\u00e6tta. E det svindel?"},{"clientName":"Bob James Max","email":"bobjames@noreply.com","message":"Hello, i want a refund"},{"clientName":"Roger Anderson","email":"anderson@yahoo.com","message":"I love the service, 10\/10, would buy again"},{"clientName":"Roger Anderson","email":"anderson@yahoo.com","message":"Hello, this is amazing, 10\/10 would buy again"}]